gptp/__init__.py
gptp/fields.py
gptp/layers.py
gptp/utils.py
scapy_gptp-0.3.0.dist-info/METADATA
scapy_gptp-0.3.0.dist-info/WHEEL
scapy_gptp-0.3.0.dist-info/licenses/LICENSE
scapy_gptp-0.3.0.dist-info/RECORD
