Metadata-Version: 2.4
Name: scapy-gptp
Version: 0.3.0
Summary: scapy layer definition and tools for GPTP (IEEE 802.1as)
Project-URL: Homepage, https://codeberg.org/weinshec/scapy-gptp
Project-URL: Repository, https://codeberg.org/weinshec/scapy-gptp
Project-URL: Issues, https://codeberg.org/weinshec/scapy-gptp/issues
Author-email: Christoph Weinsheimer <weinshec@holodeck2.de>
License-Expression: GPL-2.0
License-File: LICENSE
Keywords: 802.1as,PTP,gPTP,scapy
Classifier: Programming Language :: Python :: 3
Classifier: Programming Language :: Python :: 3.10
Classifier: Programming Language :: Python :: 3.11
Classifier: Programming Language :: Python :: 3.12
Classifier: Programming Language :: Python :: 3.13
Requires-Python: >=3.10
Requires-Dist: scapy>=2.5
